[{"packageName":"at.favre.tools.dconvert","className":"Main$1","methodSignature":"<at.favre.tools.dconvert.Main$1: onFinished(ILjava/util/List;JZLjava/lang/String;)V>","javaLine":71,"bytecodeIndex":-1,"operationType":"directlyIoSink","options":["haltOnError"],"optionCount":1,"originalStmt":"virtualinvoke $stack36.<java.io.PrintStream: void println(java.lang.String)>(log)","mayValues":[]},{"packageName":"at.favre.tools.dconvert","className":"Main$1","methodSignature":"<at.favre.tools.dconvert.Main$1: onFinished(ILjava/util/List;JZLjava/lang/String;)V>","javaLine":81,"bytecodeIndex":-1,"operationType":"directlyIoSink","options":["haltOnError"],"optionCount":1,"originalStmt":"virtualinvoke $stack29.<java.io.PrintStream: void println(java.lang.String)>($stack31)","mayValues":[]},{"packageName":"at.favre.tools.dconvert","className":"WorkerHandler","methodSignature":"<at.favre.tools.dconvert.WorkerHandler: <init>(Ljava/util/List;Lat/favre/tools/dconvert/arg/Arguments;Lat/favre/tools/dconvert/WorkerHandler$Callback;)V>","javaLine":46,"bytecodeIndex":-1,"operationType":"directlyThreadSink","options":["haltOnError"],"optionCount":1,"originalStmt":"specialinvoke $stack4.<java.util.concurrent.ThreadPoolExecutor: void <init>(int,int,long,java.util.concurrent.TimeUnit,java.util.concurrent.BlockingQueue)>($stack5, $stack6, 5L, $stack9, $stack7)","mayValues":[]},{"packageName":"at.favre.tools.dconvert","className":"Main$1","methodSignature":"<at.favre.tools.dconvert.Main$1: onProgress(F)V>","javaLine":57,"bytecodeIndex":-1,"operationType":"directlyIoSink","options":["haltOnError"],"optionCount":1,"originalStmt":"virtualinvoke $stack3.<java.io.PrintStream: void write(byte[])>($stack5)","mayValues":[]},{"packageName":"at.favre.tools.dconvert","className":"WorkerHandler","methodSignature":"<at.favre.tools.dconvert.WorkerHandler: start(Ljava/util/List;)V>","javaLine":58,"bytecodeIndex":-1,"operationType":"directlyThreadSink","options":["haltOnError"],"optionCount":1,"originalStmt":"interfaceinvoke $stack30.<java.util.concurrent.ExecutorService: void execute(java.lang.Runnable)>($stack28)","mayValues":[]},{"packageName":"at.favre.tools.dconvert.util","className":"MiscUtil","methodSignature":"<at.favre.tools.dconvert.util.MiscUtil: getStackTrace(Ljava/lang/Throwable;)Ljava/lang/String;>","javaLine":36,"bytecodeIndex":-1,"operationType":"directlyIoSink","options":["haltOnError"],"optionCount":1,"originalStmt":"specialinvoke $stack4.<java.io.PrintWriter: void <init>(java.io.Writer)>($stack3)","mayValues":[]},{"packageName":"at.favre.tools.dconvert","className":"Main$1","methodSignature":"<at.favre.tools.dconvert.Main$1: onFinished(ILjava/util/List;JZLjava/lang/String;)V>","javaLine":80,"bytecodeIndex":-1,"operationType":"loopIoSink","options":["haltOnError"],"optionCount":1,"originalStmt":"virtualinvoke $stack29.<java.io.PrintStream: void println(java.lang.String)>($stack31)","mayValues":[]},{"packageName":"at.favre.tools.dconvert","className":"Main$1","methodSignature":"<at.favre.tools.dconvert.Main$1: onFinished(ILjava/util/List;JZLjava/lang/String;)V>","javaLine":78,"bytecodeIndex":-1,"operationType":"directlyIoSink","options":["haltOnError"],"optionCount":1,"originalStmt":"virtualinvoke $stack18.<java.io.PrintStream: void println(java.lang.String)>($stack20)","mayValues":[]},{"packageName":"at.favre.tools.dconvert","className":"Main$1","methodSignature":"<at.favre.tools.dconvert.Main$1: onFinished(ILjava/util/List;JZLjava/lang/String;)V>","javaLine":65,"bytecodeIndex":-1,"operationType":"directlyIoSink","options":["haltOnError"],"optionCount":1,"originalStmt":"virtualinvoke $stack9.<java.io.PrintStream: void print(java.lang.String)>($stack10)","mayValues":[]}]