[
  {
    "packageName": "org.apache.cassandra.utils",
    "className": "FBUtilities",
    "methodSignature": "<org.apache.cassandra.utils.FBUtilities: prettyPrintMemory(JZ)Ljava/lang/String;>",
    "javaLine": 876,
    "bytecodeIndex": -1,
    "operationType": "ifNewArrSink",
    "options": [
      "networking_cache_size_in_mb"
    ],
    "optionCount": 1,
    "originalStmt": "$stack5 = newarray (java.lang.Object)[2]",
    "mayValues": []
  },
  {
    "packageName": "org.apache.cassandra.utils",
    "className": "FBUtilities",
    "methodSignature": "<org.apache.cassandra.utils.FBUtilities: prettyPrintMemory(JZ)Ljava/lang/String;>",
    "javaLine": 876,
    "bytecodeIndex": -1,
    "operationType": "ifNewArrSink",
    "options": [
      "networking_cache_size_in_mb"
    ],
    "optionCount": 1,
    "originalStmt": "$stack14 = newarray (java.lang.Object)[2]",
    "mayValues": []
  },
  {
    "packageName": "org.apache.cassandra.utils",
    "className": "FBUtilities",
    "methodSignature": "<org.apache.cassandra.utils.FBUtilities: prettyPrintMemory(JZ)Ljava/lang/String;>",
    "javaLine": 876,
    "bytecodeIndex": -1,
    "operationType": "ifNewArrSink",
    "options": [
      "networking_cache_size_in_mb"
    ],
    "optionCount": 1,
    "originalStmt": "$stack23 = newarray (java.lang.Object)[2]",
    "mayValues": []
  },
  {
    "packageName": "org.apache.cassandra.utils",
    "className": "FBUtilities",
    "methodSignature": "<org.apache.cassandra.utils.FBUtilities: prettyPrintMemory(JZ)Ljava/lang/String;>",
    "javaLine": 878,
    "bytecodeIndex": -1,
    "operationType": "ifNewArrSink",
    "options": [
      "networking_cache_size_in_mb"
    ],
    "optionCount": 1,
    "originalStmt": "$stack5 = newarray (java.lang.Object)[2]",
    "mayValues": []
  },
  {
    "packageName": "org.apache.cassandra.utils",
    "className": "FBUtilities",
    "methodSignature": "<org.apache.cassandra.utils.FBUtilities: prettyPrintMemory(JZ)Ljava/lang/String;>",
    "javaLine": 878,
    "bytecodeIndex": -1,
    "operationType": "ifNewArrSink",
    "options": [
      "networking_cache_size_in_mb"
    ],
    "optionCount": 1,
    "originalStmt": "$stack14 = newarray (java.lang.Object)[2]",
    "mayValues": []
  },
  {
    "packageName": "org.apache.cassandra.concurrent",
    "className": "InfiniteLoopExecutor",
    "methodSignature": "<org.apache.cassandra.concurrent.InfiniteLoopExecutor: <init>(Ljava/lang/String;Lorg/apache/cassandra/concurrent/InfiniteLoopExecutor$InterruptibleRunnable;)V>",
    "javaLine": 44,
    "bytecodeIndex": -1,
    "operationType": "directlyThreadSink",
    "options": [
      "networking_cache_size_in_mb"
    ],
    "optionCount": 1,
    "originalStmt": "specialinvoke $stack3.<java.lang.Thread: void <init>(java.lang.Runnable,java.lang.String)>($stack4, name)",
    "mayValues": []
  }
]